{
  "$schema": "https://developer.microsoft.com/json-schemas/fabric/item/report/definition/page/2.0.0/schema.json",
  "name": "7e40a91e15cd5c61d79e",
  "displayName": "Page 2",
  "displayOption": "FitToPage",
  "height": 720,
  "width": 1280,
  "filterConfig": {
    "filters": [
      {
        "name": "9f200d7283062c43989c",
        "field": {
          "Column": {
            "Expression": {
              "SourceRef": {
                "Entity": "brickeconomy_starwars_eur"
              }
            },
            "Property": "subtheme"
          }
        },
        "type": "Categorical",
        "filter": {
          "Version": 2,
          "From": [
            {
              "Name": "b",
              "Entity": "brickeconomy_starwars_eur",
              "Type": 0
            }
          ],
          "Where": [
            {
              "Condition": {
                "In": {
                  "Expressions": [
                    {
                      "Column": {
                        "Expression": {
                          "SourceRef": {
                            "Source": "b"
                          }
                        },
                        "Property": "subtheme"
                      }
                    }
                  ],
                  "Values": [
                    [
                      {
                        "Literal": {
                          "Value": "'Episode III'"
                        }
                      }
                    ]
                  ]
                }
              }
            }
          ]
        },
        "howCreated": "User"
      }
    ]
  }
}